{
    "code": 1,
    "desc": "success",
    "data": {
        "classId": 50,
        "courseInfoId": 1,
        "tuition": 1000.0,
        "costNumber": 100,
        "quotaNumber": 100,
        "signupCourseCharges": [
            {
                "id": 241,
                "classId": 50,
                "courseInfoId": 1,
                "courseType": "1",
                "teacherId": 334,
                "teacherName": "测试老师七",
                "teacherType": "1",
                "teacherLevelName": null,
                "classPeriod": 10,
                "chargesPrice": 5000.0,
                "createDate": null,
                "creatorId": null,
                "updateDate": null,
                "updatorId": null
            },
            {
                "id": 242,
                "classId": 50,
                "courseInfoId": 1,
                "courseType": "2",
                "teacherId": 335,
                "teacherName": "测试老师八",
                "teacherType": "2",
                "teacherLevelName": null,
                "classPeriod": 10,
                "chargesPrice": 5000.0,
                "createDate": null,
                "creatorId": null,
                "updateDate": null,
                "updatorId": null
            }
        ],
        "signupOtherCharges": [
            {
                "id": 273,
                "classId": 50,
                "courseInfoId": 1,
                "chargesName": "场地费用",
                "chargesPrice": 10000.0,
                "createDate": null,
                "creatorId": null,
                "updateDate": null,
                "updatorId": null
            },
            {
                "id": 274,
                "classId": 50,
                "courseInfoId": 1,
                "chargesName": "资料费",
                "chargesPrice": 590.0,
                "createDate": null,
                "creatorId": null,
                "updateDate": null,
                "updatorId": null
            },
            {
                "id": 275,
                "classId": 50,
                "courseInfoId": 1,
                "chargesName": "辅导课酬",
                "chargesPrice": 8800.0,
                "createDate": null,
                "creatorId": null,
                "updateDate": null,
                "updatorId": null
            }
        ],
        "signupTextbookCharges": [
            {
                "id": 365,
                "classId": 50,
                "courseInfoId": 1,
                "textbookId": 1,
                "textbookName": "《2陶渊明集》",
                "textbookPrice": 10.0,
                "createDate": null,
                "creatorId": null,
                "updateDate": null,
                "updatorId": null,
                "courseType": 1
            },
            {
                "id": 366,
                "classId": 50,
                "courseInfoId": 1,
                "textbookId": 2,
                "textbookName": "《2老子》",
                "textbookPrice": 10.0,
                "createDate": null,
                "creatorId": null,
                "updateDate": null,
                "updatorId": null,
                "courseType": 1
            },
            {
                "id": 367,
                "classId": 50,
                "courseInfoId": 1,
                "textbookId": 3,
                "textbookName": "《2东坡乐府》",
                "textbookPrice": 10.0,
                "createDate": null,
                "creatorId": null,
                "updateDate": null,
                "updatorId": null,
                "courseType": 1
            },
            {
                "id": 368,
                "classId": 50,
                "courseInfoId": 1,
                "textbookId": 4,
                "textbookName": "《2论语》",
                "textbookPrice": 10.0,
                "createDate": null,
                "creatorId": null,
                "updateDate": null,
                "updatorId": null,
                "courseType": 1
            },
            {
                "id": 369,
                "classId": 50,
                "courseInfoId": 1,
                "textbookId": 5,
                "textbookName": "《2古史辨》",
                "textbookPrice": 10.0,
                "createDate": null,
                "creatorId": null,
                "updateDate": null,
                "updatorId": null,
                "courseType": 1
            },
            {
                "id": 370,
                "classId": 50,
                "courseInfoId": 1,
                "textbookId": 26,
                "textbookName": "《独秀文存》",
                "textbookPrice": 10.0,
                "createDate": null,
                "creatorId": null,
                "updateDate": null,
                "updatorId": null,
                "courseType": 2
            },
            {
                "id": 371,
                "classId": 50,
                "courseInfoId": 1,
                "textbookId": 27,
                "textbookName": "《欧洲文明史》",
                "textbookPrice": 10.0,
                "createDate": null,
                "creatorId": null,
                "updateDate": null,
                "updatorId": null,
                "courseType": 2
            },
            {
                "id": 372,
                "classId": 50,
                "courseInfoId": 1,
                "textbookId": 28,
                "textbookName": "《路易·波拿巴的雾月十八日》",
                "textbookPrice": 10.0,
                "createDate": null,
                "creatorId": null,
                "updateDate": null,
                "updatorId": null,
                "courseType": 2
            },
            {
                "id": 373,
                "classId": 50,
                "courseInfoId": 1,
                "textbookId": 29,
                "textbookName": "《德意志意识形态》",
                "textbookPrice": 10.0,
                "createDate": null,
                "creatorId": null,
                "updateDate": null,
                "updatorId": null,
                "courseType": 2
            },
            {
                "id": 374,
                "classId": 50,
                "courseInfoId": 1,
                "textbookId": 210,
                "textbookName": "《狄德罗哲学选集》",
                "textbookPrice": 10.0,
                "createDate": null,
                "creatorId": null,
                "updateDate": null,
                "updatorId": null,
                "courseType": 2
            }
        ]
    },
    "token": null,
    "list": null,
    "recordCount": null
}